MANIFEST.in
README.txt
setup.cfg
setup.py
docs/HISTORY.txt
docs/extending.rst
docs/glossary.rst
docs/index.rst
docs/innerworkings.rst
docs/installation.rst
docs/usage.rst
pydataportability/__init__.py
pydataportability.discovery.egg-info/PKG-INFO
pydataportability.discovery.egg-info/SOURCES.txt
pydataportability.discovery.egg-info/dependency_links.txt
pydataportability.discovery.egg-info/entry_points.txt
pydataportability.discovery.egg-info/namespace_packages.txt
pydataportability.discovery.egg-info/not-zip-safe
pydataportability.discovery.egg-info/requires.txt
pydataportability.discovery.egg-info/top_level.txt
pydataportability/discovery/__init__.py
pydataportability/discovery/acctservice.py
pydataportability/discovery/configure.zcml
pydataportability/discovery/discovery.py
pydataportability/discovery/hostmeta.py
pydataportability/discovery/httpheader.py
pydataportability/discovery/interfaces.py
pydataportability/discovery/network.py
pydataportability/discovery/relationshipresolver.py
pydataportability/discovery/tests/__init__.py
pydataportability/discovery/tests/configurator.py
pydataportability/discovery/tests/conftest.py
pydataportability/discovery/tests/network.py
pydataportability/discovery/tests/test_acct.py
pydataportability/discovery/tests/test_hostmeta.py
pydataportability/discovery/tests/test_rel_resolver.py