Metadata-Version: 1.0
Name: pydataportability.discovery
Version: 0.4
Summary: Christian Scholz
Home-page: http://pydataportability.org
Author: Christian Scholz
Author-email: cs@comlounge.net
License: BSD
Keywords: pydataportability dataportability acct xrd discovery webfinger finger google
Platform: UNKNOWN
Classifier: Programming Language :: Python
Classifier: Topic :: Software Development :: Libraries :: Python Modules
